plotly_cloud/__init__.py
plotly_cloud/_api_types.py
plotly_cloud/_changes.py
plotly_cloud/_cloud_env.py
plotly_cloud/_commands.py
plotly_cloud/_definitions.py
plotly_cloud/_deploy.py
plotly_cloud/_devtool_hooks.py
plotly_cloud/_devtool_publish_rpc.py
plotly_cloud/_oauth.py
plotly_cloud/_parser.py
plotly_cloud/cli.py
plotly_cloud/cloud-env.toml
plotly_cloud/cloud_devtools.css
plotly_cloud/cloud_devtools.js
plotly_cloud/exceptions.py
plotly_cloud-0.1.0rc5.dist-info/METADATA
plotly_cloud-0.1.0rc5.dist-info/WHEEL
plotly_cloud-0.1.0rc5.dist-info/entry_points.txt
plotly_cloud-0.1.0rc5.dist-info/licenses/LICENSE
plotly_cloud-0.1.0rc5.dist-info/RECORD
