Metadata-Version: 2.4
Name: plotly-cloud
Version: 0.1.0rc5
Summary: CLI for interacting with Plotly Cloud to deploy Dash apps
License-File: LICENSE
Requires-Python: >=3.9
Requires-Dist: dash>=2.0.0
Requires-Dist: httpx<1.0.0,>=0.24.0
Requires-Dist: nest-asyncio>=1.6.0
Requires-Dist: rich-argparse>=1.7.1
Requires-Dist: rich>=10.0.0
Requires-Dist: tomli-w>=1.2.0
Requires-Dist: tomli>=2.2.1
